README.md
setup.py
clone/__init__.py
clone/common/__init__.py
clone/common/clone_process.py
clone/config/__init__.py
clone/config/netezza_config.py
clone/helper/__init__.py
clone/helper/file_operations.py
clone/helper/git_operations.py
demos/__init__.py
demos/demo_nz.py
demos/test_fs_and_s3.py
demos/test_netezza.py
demos/test_stuff.py
hashmap_data_migrator.egg-info/PKG-INFO
hashmap_data_migrator.egg-info/SOURCES.txt
hashmap_data_migrator.egg-info/dependency_links.txt
hashmap_data_migrator.egg-info/top_level.txt
hdm/__init__.py
hdm/data_link.py
hdm/data_link_builder.py
hdm/hashmap_data_migrator.py
hdm/migration_driver.py
hdm/core/__init__.py
hdm/core/catalog/__init__.py
hdm/core/catalog/crawler/__init__.py
hdm/core/catalog/crawler/netezza_crawler.py
hdm/core/catalog/ddl_writer/__init__.py
hdm/core/catalog/ddl_writer/snowflake_ddl_writer.py
hdm/core/catalog/mapper/__init__.py
hdm/core/catalog/mapper/netezza_to_snowflake_mapper.py
hdm/core/dao/__init__.py
hdm/core/dao/azure_blob.py
hdm/core/dao/azure_sql_server.py
hdm/core/dao/dao.py
hdm/core/dao/db_dao.py
hdm/core/dao/mysql.py
hdm/core/dao/netezza.py
hdm/core/dao/netezza_jdbc.py
hdm/core/dao/netezza_odbc.py
hdm/core/dao/object_store_dao.py
hdm/core/dao/s3.py
hdm/core/dao/snowflake.py
hdm/core/dao/snowflake_azure_copy.py
hdm/core/dao/snowflake_copy.py
hdm/core/dao/snowflake_gcp_copy.py
hdm/core/dao/snowflake_s3_copy.py
hdm/core/dao/sql_server.py
hdm/core/dao/sqlite.py
hdm/core/error/__init__.py
hdm/core/error/hdm_error.py
hdm/core/orchestrator/__init__.py
hdm/core/orchestrator/auto_orchestrator.py
hdm/core/orchestrator/batch_orchestrator.py
hdm/core/orchestrator/declared_orchestrator.py
hdm/core/orchestrator/orchestrator.py
hdm/core/sink/__init__.py
hdm/core/sink/azure_blob_sink.py
hdm/core/sink/dummy_sink.py
hdm/core/sink/fs_sink.py
hdm/core/sink/google_sink.py
hdm/core/sink/mysql_sink.py
hdm/core/sink/netezza_sink.py
hdm/core/sink/rdbms_sink.py
hdm/core/sink/s3_sink.py
hdm/core/sink/sink.py
hdm/core/sink/snowflake_azure_copy_sink.py
hdm/core/sink/snowflake_copy_sink.py
hdm/core/sink/snowflake_internal_stage_sink.py
hdm/core/source/__init__.py
hdm/core/source/azure_blob_source.py
